Testbench/voting_machine.v
// File: voting_machine.v

// Button Debounce and Valid Vote Detection (Active High)
module buttonControl(
    input clock,                 // System clock input
    input reset,                 // Active high synchronous reset input
    input button,                // Active high button input for voting
    output reg valid_vote        // Output: high for one clock when a valid vote is detected
);
    reg [6:0] counter;          // Counter to measure button press duration

    always @(posedge clock) begin
        if (reset)               // If reset is high (reset active)
            counter <= 0;        //   Reset counter to zero
        else begin
            if (button && counter < 101) // If button is pressed (active high) and counter not maxed
                counter <= counter + 1;  //   Increment counter
            else if (!button)            // If button is released (not pressed)
                counter <= 0;            //   Reset counter
        end
    end

    always @(posedge clock) begin
        if (reset)               // If reset is high (reset active)
            valid_vote <= 1'b0;  //   Clear valid_vote output
        else begin
            if (counter == 100)  // If button held for 1us second (at 100MHz)
                valid_vote <= 1'b1;   //   Set valid_vote high for one clock
            else
                valid_vote <= 1'b0;   //   Otherwise, keep valid_vote low
        end
    end
endmodule

// Vote Counting Module
module voteLogger(
    input clock,                  // System clock input
    input reset,                  // Active high synchronous reset input
    input mode,                   // Mode: 0 = voting, 1 = result display
    input cand1_vote_valid,       // Valid vote for candidate 1
    input cand2_vote_valid,       // Valid vote for candidate 2
    input cand3_vote_valid,       // Valid vote for candidate 3
    input cand4_vote_valid,       // Valid vote for candidate 4
    output reg [7:0] cand1_vote_recvd, // Vote count for candidate 1
    output reg [7:0] cand2_vote_recvd, // Vote count for candidate 2
    output reg [7:0] cand3_vote_recvd, // Vote count for candidate 3
    output reg [7:0] cand4_vote_recvd  // Vote count for candidate 4
);
    always @(posedge clock) begin
        if (reset) begin                // If reset is high (reset active)
            cand1_vote_recvd <= 0;
            cand2_vote_recvd <= 0;
            cand3_vote_recvd <= 0;
            cand4_vote_recvd <= 0;
        end else if (mode == 0) begin   // If in voting mode
            if (cand1_vote_valid)
                cand1_vote_recvd <= cand1_vote_recvd + 1;
            else if (cand2_vote_valid)
                cand2_vote_recvd <= cand2_vote_recvd + 1;
            else if (cand3_vote_valid)
                cand3_vote_recvd <= cand3_vote_recvd + 1;
            else if (cand4_vote_valid)
                cand4_vote_recvd <= cand4_vote_recvd + 1;
        end
    end
endmodule

// LED and Mode Control Module
module modeControl(
    input clock,                      // System clock input
    input reset,                      // Active high synchronous reset input
    input mode,                       // Mode: 0 = voting, 1 = result display
    input valid_vote_casted,          // High for one clock when any valid vote is cast
    input [7:0] candidate1_vote,      // Vote count for candidate 1
    input [7:0] candidate2_vote,      // Vote count for candidate 2
    input [7:0] candidate3_vote,      // Vote count for candidate 3
    input [7:0] candidate4_vote,      // Vote count for candidate 4
    input candidate1_button_press,    // Button press for candidate 1 (active high)
    input candidate2_button_press,    // Button press for candidate 2 (active high)
    input candidate3_button_press,    // Button press for candidate 3 (active high)
    input candidate4_button_press,    // Button press for candidate 4 (active high)
    output reg [7:0] leds             // Output: 8-bit LED display
);
    reg [6:0] counter;               // Counter for feedback timing
    wire any_button_pressed;

    assign any_button_pressed = candidate1_button_press | candidate2_button_press |
                               candidate3_button_press | candidate4_button_press;

    always @(posedge clock) begin
        if (reset) begin
            counter <= 0;
        end else if (mode == 0) begin
            if (any_button_pressed) begin
                if (counter == 0)
                    counter <= 1; // Start counter on button press
                else if (counter < 100) // Set your desired duration here
                    counter <= counter + 1;
                // else counter holds at max value until button released
            end else begin
                counter <= 0; // Reset counter when no button is pressed
            end
        end else begin
            counter <= 0; // Reset counter in result mode
        end
    end

    always @(posedge clock) begin
        if (reset) begin
            leds <= 8'h00;
        end else if (mode == 0) begin
            if (any_button_pressed && counter < 100)
                leds <= 8'hFF; // All LEDs on immediately when button pressed
            else
                leds <= 8'h00; // LEDs off after counter expires or no button pressed
        end else begin
            // Result display mode logic
            if (candidate1_button_press)
                leds <= candidate1_vote;
            else if (candidate2_button_press)
                leds <= candidate2_vote;
            else if (candidate3_button_press)
                leds <= candidate3_vote;
            else if (candidate4_button_press)
                leds <= candidate4_vote;
            else
                leds <= 8'h00;
        end
    end
endmodule


// Top-Level Voting Machine Module
module Voting_Machine(
    input clock,                  // System clock input
    input reset,                  // Active high synchronous reset input
    input mode,                   // Mode: 0 = voting, 1 = result display
    input button1,                // Active high button input for candidate 1
    input button2,                // Active high button input for candidate 2
    input button3,                // Active high button input for candidate 3
    input button4,                // Active high button input for candidate 4
    output [7:0] led              // Output: 8-bit LED display
);

    wire valid_vote_1;
    wire valid_vote_2;
    wire valid_vote_3;
    wire valid_vote_4;
    wire [7:0] cand1_vote_recvd;
    wire [7:0] cand2_vote_recvd;
    wire [7:0] cand3_vote_recvd;
    wire [7:0] cand4_vote_recvd;
    wire anyValidVote;

    assign anyValidVote = valid_vote_1 | valid_vote_2 | valid_vote_3 | valid_vote_4;

    buttonControl bc1(
        .clock(clock),
        .reset(reset),
        .button(button1),
        .valid_vote(valid_vote_1)
    );

    buttonControl bc2(
        .clock(clock),
        .reset(reset),
        .button(button2),
        .valid_vote(valid_vote_2)
    );

    buttonControl bc3(
        .clock(clock),
        .reset(reset),
        .button(button3),
        .valid_vote(valid_vote_3)
    );

    buttonControl bc4(
        .clock(clock),
        .reset(reset),
        .button(button4),
        .valid_vote(valid_vote_4)
    );

    voteLogger VL(
        .clock(clock),
        .reset(reset),
        .mode(mode),
        .cand1_vote_valid(valid_vote_1),
        .cand2_vote_valid(valid_vote_2),
        .cand3_vote_valid(valid_vote_3),
        .cand4_vote_valid(valid_vote_4),
        .cand1_vote_recvd(cand1_vote_recvd),
        .cand2_vote_recvd(cand2_vote_recvd),
        .cand3_vote_recvd(cand3_vote_recvd),
        .cand4_vote_recvd(cand4_vote_recvd)
    );

    modeControl MC(
        .clock(clock),
        .reset(reset),
        .mode(mode),
        .valid_vote_casted(anyValidVote),
        .candidate1_vote(cand1_vote_recvd),
        .candidate2_vote(cand2_vote_recvd),
        .candidate3_vote(cand3_vote_recvd),
        .candidate4_vote(cand4_vote_recvd),
        .candidate1_button_press(button1), // Active high: pressed when 1
        .candidate2_button_press(button2),
        .candidate3_button_press(button3),
        .candidate4_button_press(button4),
        .leds(led)
    );
endmodule

Testbench/voting_machine_tb.v
`timescale 1ns/1ps
`include "voting_machine.v"

module Voting_Machine_tb;

    // Testbench signals
    reg clock;
    reg reset;
    reg mode;
    reg button1, button2, button3, button4;
    wire [7:0] led;

    // Instantiate the DUT
    Voting_Machine uut (
        .clock(clock),
        .reset(reset),
        .mode(mode),
        .button1(button1),
        .button2(button2),
        .button3(button3),
        .button4(button4),
        .led(led)
    );

    // Clock generation: 50MHz (20ns period)
    initial begin
        clock = 0;
        forever #10 clock = ~clock;
    end

    initial begin
        $dumpfile("voting_machine_tb.vcd");
        $dumpvars(0, Voting_Machine_tb);
    end

    // Test sequence
    initial begin
        // Initialize inputs
        reset = 1;
        mode = 0; // Voting mode
        button1 = 0;
        button2 = 0;
        button3 = 0;
        button4 = 0;

        // Apply reset
        #50;
        reset = 0;

        // Wait for system to stabilize
        #100;

        // Simulate voting for candidate 1 (hold button for >100 clocks)
        button1 = 1;
        #2200; // 110 clock cycles (20ns * 110 = 2200ns)
        button1 = 0;
        #500;

        // Unvalid vote 
        button1 = 1;
        #1200; 
        button1 = 0;
        #500;


        // Simulate voting for candidate 2
        button2 = 1;
        #2200;
        button2 = 0;
        #500;

        // Simulate voting for candidate 3
        button3 = 1;
        #2200;
        button3 = 0;
        #500;

        // Simulate voting for candidate 4
        button4 = 1;
        #2200;
        button4 = 0;
        #500;

        // Simulate a second vote for candidate 1
        button1 = 1;
        #2200;
        button1 = 0;
        #500;

        // Switch to result display mode
        mode = 1;
        #200;

        // Display candidate 1's vote count
        button1 = 1;
        #200;
        button1 = 0;
        #200;

        // Display candidate 2's vote count
        button2 = 1;
        #200;
        button2 = 0;
        #200;

        // Display candidate 3's vote count
        button3 = 1;
        #200;
        button3 = 0;
        #200;

        // Display candidate 4's vote count
        button4 = 1;
        #200;
        button4 = 0;
        #200;

        // End simulation
        $finish;
    end

    // Monitor outputs
    initial begin
        $monitor("Time=%0t | mode=%b | btn1=%b btn2=%b btn3=%b btn4=%b | led=%h", 
                 $time, mode, button1, button2, button3, button4, led, "\n");
    end

endmodule

Testbench/voting_machine_tb.vcd
$date
	Fri Jul 04 13:14:46 2025
$end
$version
	Icarus Verilog
$end
$timescale
	1ps
$end
$scope module Voting_Machine_tb $end
$var wire 8 ! led [7:0] $end
$var reg 1 " button1 $end
$var reg 1 # button2 $end
$var reg 1 $ button3 $end
$var reg 1 % button4 $end
$var reg 1 & clock $end
$var reg 1 ' mode $end
$var reg 1 ( reset $end
$scope module uut $end
$var wire 1 ) anyValidVote $end
$var wire 1 " button1 $end
$var wire 1 # button2 $end
$var wire 1 $ button3 $end
$var wire 1 % button4 $end
$var wire 1 & clock $end
$var wire 1 ' mode $end
$var wire 1 ( reset $end
$var wire 1 * valid_vote_4 $end
$var wire 1 + valid_vote_3 $end
$var wire 1 , valid_vote_2 $end
$var wire 1 - valid_vote_1 $end
$var wire 8 . led [7:0] $end
$var wire 8 / cand4_vote_recvd [7:0] $end
$var wire 8 0 cand3_vote_recvd [7:0] $end
$var wire 8 1 cand2_vote_recvd [7:0] $end
$var wire 8 2 cand1_vote_recvd [7:0] $end
$scope module MC $end
$var wire 1 3 any_button_pressed $end
$var wire 1 " candidate1_button_press $end
$var wire 1 # candidate2_button_press $end
$var wire 1 $ candidate3_button_press $end
$var wire 1 % candidate4_button_press $end
$var wire 1 & clock $end
$var wire 1 ' mode $end
$var wire 1 ( reset $end
$var wire 1 ) valid_vote_casted $end
$var wire 8 4 candidate4_vote [7:0] $end
$var wire 8 5 candidate3_vote [7:0] $end
$var wire 8 6 candidate2_vote [7:0] $end
$var wire 8 7 candidate1_vote [7:0] $end
$var reg 7 8 counter [6:0] $end
$var reg 8 9 leds [7:0] $end
$upscope $end
$scope module VL $end
$var wire 1 & clock $end
$var wire 1 ' mode $end
$var wire 1 ( reset $end
$var wire 1 * cand4_vote_valid $end
$var wire 1 + cand3_vote_valid $end
$var wire 1 , cand2_vote_valid $end
$var wire 1 - cand1_vote_valid $end
$var reg 8 : cand1_vote_recvd [7:0] $end
$var reg 8 ; cand2_vote_recvd [7:0] $end
$var reg 8 < cand3_vote_recvd [7:0] $end
$var reg 8 = cand4_vote_recvd [7:0] $end
$upscope $end
$scope module bc1 $end
$var wire 1 " button $end
$var wire 1 & clock $end
$var wire 1 ( reset $end
$var reg 7 > counter [6:0] $end
$var reg 1 - valid_vote $end
$upscope $end
$scope module bc2 $end
$var wire 1 # button $end
$var wire 1 & clock $end
$var wire 1 ( reset $end
$var reg 7 ? counter [6:0] $end
$var reg 1 , valid_vote $end
$upscope $end
$scope module bc3 $end
$var wire 1 $ button $end
$var wire 1 & clock $end
$var wire 1 ( reset $end
$var reg 7 @ counter [6:0] $end
$var reg 1 + valid_vote $end
$upscope $end
$scope module bc4 $end
$var wire 1 % button $end
$var wire 1 & clock $end
$var wire 1 ( reset $end
$var reg 7 A counter [6:0] $end
$var reg 1 * valid_vote $end
$upscope $end
$upscope $end
$upscope $end
$enddefinitions $end
#0
$dumpvars
bx A
bx @
bx ?
bx >
bx =
bx <
bx ;
bx :
bx 9
bx 8
bx 7
bx 6
bx 5
bx 4
03
bx 2
bx 1
bx 0
bx /
bx .
x-
x,
x+
x*
x)
1(
0'
0&
0%
0$
0#
0"
bx !
$end
#10000
0)
b0 >
0-
b0 ?
0,
b0 @
0+
b0 A
0*
b0 /
b0 4
b0 =
b0 0
b0 5
b0 <
b0 1
b0 6
b0 ;
b0 2
b0 7
b0 :
b0 8
b0 !
b0 .
b0 9
1&
#20000
0&
#30000
1&
#40000
0&
#50000
1&
0(
#60000
0&
#70000
1&
#80000
0&
#90000
1&
#100000
0&
#110000
1&
#120000
0&
#130000
1&
#140000
0&
#150000
b1 >
13
1&
1"
#160000
0&
#170000
b10 >
b1 8
b11111111 !
b11111111 .
b11111111 9
1&
#180000
0&
#190000
b10 8
b11 >
1&
#200000
0&
#210000
b100 >
b11 8
1&
#220000
0&
#230000
b100 8
b101 >
1&
#240000
0&
#250000
b110 >
b101 8
1&
#260000
0&
#270000
b110 8
b111 >
1&
#280000
0&
#290000
b1000 >
b111 8
1&
#300000
0&
#310000
b1000 8
b1001 >
1&
#320000
0&
#330000
b1010 >
b1001 8
1&
#340000
0&
#350000
b1010 8
b1011 >
1&
#360000
0&
#370000
b1100 >
b1011 8
1&
#380000
0&
#390000
b1100 8
b1101 >
1&
#400000
0&
#410000
b1110 >
b1101 8
1&
#420000
0&
#430000
b1110 8
b1111 >
1&
#440000
0&
#450000
b10000 >
b1111 8
1&
#460000
0&
#470000
b10000 8
b10001 >
1&
#480000
0&
#490000
b10010 >
b10001 8
1&
#500000
0&
#510000
b10010 8
b10011 >
1&
#520000
0&
#530000
b10100 >
b10011 8
1&
#540000
0&
#550000
b10100 8
b10101 >
1&
#560000
0&
#570000
b10110 >
b10101 8
1&
#580000
0&
#590000
b10110 8
b10111 >
1&
#600000
0&
#610000
b11000 >
b10111 8
1&
#620000
0&
#630000
b11000 8
b11001 >
1&
#640000
0&
#650000
b11010 >
b11001 8
1&
#660000
0&
#670000
b11010 8
b11011 >
1&
#680000
0&
#690000
b11100 >
b11011 8
1&
#700000
0&
#710000
b11100 8
b11101 >
1&
#720000
0&
#730000
b11110 >
b11101 8
1&
#740000
0&
#750000
b11110 8
b11111 >
1&
#760000
0&
#770000
b100000 >
b11111 8
1&
#780000
0&
#790000
b100000 8
b100001 >
1&
#800000
0&
#810000
b100010 >
b100001 8
1&
#820000
0&
#830000
b100010 8
b100011 >
1&
#840000
0&
#850000
b100100 >
b100011 8
1&
#860000
0&
#870000
b100100 8
b100101 >
1&
#880000
0&
#890000
b100110 >
b100101 8
1&
#900000
0&
#910000
b100110 8
b100111 >
1&
#920000
0&
#930000
b101000 >
b100111 8
1&
#940000
0&
#950000
b101000 8
b101001 >
1&
#960000
0&
#970000
b101010 >
b101001 8
1&
#980000
0&
#990000
b101010 8
b101011 >
1&
#1000000
0&
#1010000
b101100 >
b101011 8
1&
#1020000
0&
#1030000
b101100 8
b101101 >
1&
#1040000
0&
#1050000
b101110 >
b101101 8
1&
#1060000
0&
#1070000
b101110 8
b101111 >
1&
#1080000
0&
#1090000
b110000 >
b101111 8
1&
#1100000
0&
#1110000
b110000 8
b110001 >
1&
#1120000
0&
#1130000
b110010 >
b110001 8
1&
#1140000
0&
#1150000
b110010 8
b110011 >
1&
#1160000
0&
#1170000
b110100 >
b110011 8
1&
#1180000
0&
#1190000
b110100 8
b110101 >
1&
#1200000
0&
#1210000
b110110 >
b110101 8
1&
#1220000
0&
#1230000
b110110 8
b110111 >
1&
#1240000
0&
#1250000
b111000 >
b110111 8
1&
#1260000
0&
#1270000
b111000 8
b111001 >
1&
#1280000
0&
#1290000
b111010 >
b111001 8
1&
#1300000
0&
#1310000
b111010 8
b111011 >
1&
#1320000
0&
#1330000
b111100 >
b111011 8
1&
#1340000
0&
#1350000
b111100 8
b111101 >
1&
#1360000
0&
#1370000
b111110 >
b111101 8
1&
#1380000
0&
#1390000
b111110 8
b111111 >
1&
#1400000
0&
#1410000
b1000000 >
b111111 8
1&
#1420000
0&
#1430000
b1000000 8
b1000001 >
1&
#1440000
0&
#1450000
b1000010 >
b1000001 8
1&
#1460000
0&
#1470000
b1000010 8
b1000011 >
1&
#1480000
0&
#1490000
b1000100 >
b1000011 8
1&
#1500000
0&
#1510000
b1000100 8
b1000101 >
1&
#1520000
0&
#1530000
b1000110 >
b1000101 8
1&
#1540000
0&
#1550000
b1000110 8
b1000111 >
1&
#1560000
0&
#1570000
b1001000 >
b1000111 8
1&
#1580000
0&
#1590000
b1001000 8
b1001001 >
1&
#1600000
0&
#1610000
b1001010 >
b1001001 8
1&
#1620000
0&
#1630000
b1001010 8
b1001011 >
1&
#1640000
0&
#1650000
b1001100 >
b1001011 8
1&
#1660000
0&
#1670000
b1001100 8
b1001101 >
1&
#1680000
0&
#1690000
b1001110 >
b1001101 8
1&
#1700000
0&
#1710000
b1001110 8
b1001111 >
1&
#1720000
0&
#1730000
b1010000 >
b1001111 8
1&
#1740000
0&
#1750000
b1010000 8
b1010001 >
1&
#1760000
0&
#1770000
b1010010 >
b1010001 8
1&
#1780000
0&
#1790000
b1010010 8
b1010011 >
1&
#1800000
0&
#1810000
b1010100 >
b1010011 8
1&
#1820000
0&
#1830000
b1010100 8
b1010101 >
1&
#1840000
0&
#1850000
b1010110 >
b1010101 8
1&
#1860000
0&
#1870000
b1010110 8
b1010111 >
1&
#1880000
0&
#1890000
b1011000 >
b1010111 8
1&
#1900000
0&
#1910000
b1011000 8
b1011001 >
1&
#1920000
0&
#1930000
b1011010 >
b1011001 8
1&
#1940000
0&
#1950000
b1011010 8
b1011011 >
1&
#1960000
0&
#1970000
b1011100 >
b1011011 8
1&
#1980000
0&
#1990000
b1011100 8
b1011101 >
1&
#2000000
0&
#2010000
b1011110 >
b1011101 8
1&
#2020000
0&
#2030000
b1011110 8
b1011111 >
1&
#2040000
0&
#2050000
b1100000 >
b1011111 8
1&
#2060000
0&
#2070000
b1100000 8
b1100001 >
1&
#2080000
0&
#2090000
b1100010 >
b1100001 8
1&
#2100000
0&
#2110000
b1100010 8
b1100011 >
1&
#2120000
0&
#2130000
b1100100 >
b1100011 8
1&
#2140000
0&
#2150000
1)
b1100100 8
1-
b1100101 >
1&
#2160000
0&
#2170000
0)
0-
b1 2
b1 7
b1 :
b0 !
b0 .
b0 9
1&
#2180000
0&
#2190000
1&
#2200000
0&
#2210000
1&
#2220000
0&
#2230000
1&
#2240000
0&
#2250000
1&
#2260000
0&
#2270000
1&
#2280000
0&
#2290000
1&
#2300000
0&
#2310000
1&
#2320000
0&
#2330000
1&
#2340000
0&
#2350000
b0 >
03
1&
0"
#2360000
0&
#2370000
b0 8
1&
